M5_project/__init__.py
M5_project/m5_initial_nn_model.py
M5_project-1.0.0.data/scripts/m5_initial_nn_model.py
M5_project-1.0.0.dist-info/METADATA
M5_project-1.0.0.dist-info/WHEEL
M5_project-1.0.0.dist-info/top_level.txt
M5_project-1.0.0.dist-info/RECORD
