Metadata-Version: 2.1
Name: M5-project
Version: 1.0.0
Summary: Initial NN model for M5 project
Author: Boris
License: UNKNOWN
Project-URL: Git url, https://github.com/borisilin85/M5_project
Platform: UNKNOWN
Requires-Python: >=3.7
Requires-Dist: tensorflow
Requires-Dist: numpy
Requires-Dist: pandas
